sparklen/__init__.py
sparklen/array/__init__.py
sparklen/array/build/__init__.py
sparklen/array/build/_array.cp311-win_amd64.pyd
sparklen/array/build/array.py
sparklen/array/build/array_wrap.cxx
sparklen/calibration/__init__.py
sparklen/calibration/calibration_cv.py
sparklen/calibration/calibration_ebic.py
sparklen/calibration/base/__init__.py
sparklen/calibration/base/calibration.py
sparklen/hawkes/__init__.py
sparklen/hawkes/classification/__init__.py
sparklen/hawkes/classification/erm_classifier.py
sparklen/hawkes/classification/ermlr_classifier.py
sparklen/hawkes/classification/sample_generator.py
sparklen/hawkes/inference/__init__.py
sparklen/hawkes/inference/learner_hawkes_exp.py
sparklen/hawkes/model/__init__.py
sparklen/hawkes/model/model_hawkes_exp_classification.py
sparklen/hawkes/model/model_hawkes_exp_least_squares.py
sparklen/hawkes/model/model_hawkes_exp_log_likelihood.py
sparklen/hawkes/model/base/__init__.py
sparklen/hawkes/model/base/model_hawkes.py
sparklen/hawkes/model/base/model_hawkes_classification.py
sparklen/hawkes/model/build/__init__.py
sparklen/hawkes/model/build/_hawkes_model.cp311-win_amd64.pyd
sparklen/hawkes/model/build/hawkes_model.py
sparklen/hawkes/model/build/hawkes_model_wrap.cxx
sparklen/hawkes/simulation/__init__.py
sparklen/hawkes/simulation/simu_hawkes_exp.py
sparklen/optim/__init__.py
sparklen/optim/lr/__init__.py
sparklen/optim/lr/backtracking_line_search_lr.py
sparklen/optim/lr/lipschitz_lr.py
sparklen/optim/lr/base/__init__.py
sparklen/optim/lr/base/learning_rate.py
sparklen/optim/optimizer/__init__.py
sparklen/optim/optimizer/agd.py
sparklen/optim/optimizer/gd.py
sparklen/optim/optimizer/base/__init__.py
sparklen/optim/optimizer/base/optimizer.py
sparklen/optim/optimizer/build/__init__.py
sparklen/optim/optimizer/build/optimizer.py
sparklen/plot/__init__.py
sparklen/plot/plot_hawkes.py
sparklen/plot/plot_utils.py
sparklen/prox/__init__.py
sparklen/prox/prox_elastic_net.py
sparklen/prox/prox_l1.py
sparklen/prox/prox_l2.py
sparklen-1.0.0.dist-info/LICENSE.txt
sparklen-1.0.0.dist-info/METADATA
sparklen-1.0.0.dist-info/WHEEL
sparklen-1.0.0.dist-info/top_level.txt
sparklen-1.0.0.dist-info/RECORD
