Metadata-Version: 2.1
Name: sparklen
Version: 1.0.0
Summary: A statistical learning toolkit for high-dimensional Hawkes processes in Python
Author-email: "Romain E. Lacoste" <romain.lacoste@polytechnique.edu>
Maintainer-email: "Romain E. Lacoste" <romain.lacoste@polytechnique.edu>
License: BSD 3-Clause License
Project-URL: Homepage, https://github.com/romain-e-lacoste/sparklen
Project-URL: Repository, https://github.com/romain-e-lacoste/sparklen.git
Keywords: python,machine-learning,statistics,optimization,regularization,maximum-likelihood-estimation,high-dimension,hawkes-process,empirical-risk-minimization
Classifier: Development Status :: 4 - Beta
Classifier: Intended Audience :: Science/Research
Classifier: Intended Audience :: Developers
Classifier: Programming Language :: C++
Classifier: Programming Language :: Python
Classifier: Topic :: Software Development :: Libraries
Classifier: Topic :: Scientific/Engineering
Classifier: Operating System :: POSIX :: Linux
Classifier: Operating System :: Microsoft :: Windows
Classifier: Operating System :: MacOS
Classifier: Programming Language :: Python :: 3
Classifier: Programming Language :: Python :: 3.10
Classifier: Programming Language :: Python :: 3.11
Classifier: Programming Language :: Python :: 3.12
Classifier: License :: OSI Approved :: BSD License
Requires-Python: >=3.8
License-File: LICENSE.txt
Requires-Dist: matplotlib
Requires-Dist: numpy
Requires-Dist: pandas
Requires-Dist: scipy
Requires-Dist: seaborn
Requires-Dist: scikit-learn
Requires-Dist: tabulate
Requires-Dist: tqdm
